sphinxjp.themes.revealjs-0.3.0-py2.7-nspkg.pth
sphinxjp/themes/revealjs/__init__.py
sphinxjp/themes/revealjs/compat.py
sphinxjp/themes/revealjs/directives.py
sphinxjp/themes/revealjs/templates/revealjs/layout.html
sphinxjp/themes/revealjs/templates/revealjs/theme.conf
sphinxjp/themes/revealjs/templates/revealjs/static/revealjs.css_t
sphinxjp/themes/revealjs/templates/revealjs/static/css/reveal.css
sphinxjp/themes/revealjs/templates/revealjs/static/css/reveal.min.css
sphinxjp/themes/revealjs/templates/revealjs/static/css/print/paper.css
sphinxjp/themes/revealjs/templates/revealjs/static/css/print/pdf.css
sphinxjp/themes/revealjs/templates/revealjs/static/css/theme/beige.css
sphinxjp/themes/revealjs/templates/revealjs/static/css/theme/black.css
sphinxjp/themes/revealjs/templates/revealjs/static/css/theme/blood.css
sphinxjp/themes/revealjs/templates/revealjs/static/css/theme/default.css
sphinxjp/themes/revealjs/templates/revealjs/static/css/theme/league.css
sphinxjp/themes/revealjs/templates/revealjs/static/css/theme/moon.css
sphinxjp/themes/revealjs/templates/revealjs/static/css/theme/night.css
sphinxjp/themes/revealjs/templates/revealjs/static/css/theme/serif.css
sphinxjp/themes/revealjs/templates/revealjs/static/css/theme/simple.css
sphinxjp/themes/revealjs/templates/revealjs/static/css/theme/sky.css
sphinxjp/themes/revealjs/templates/revealjs/static/css/theme/solarized.css
sphinxjp/themes/revealjs/templates/revealjs/static/css/theme/white.css
sphinxjp/themes/revealjs/templates/revealjs/static/js/jquery.min.js
sphinxjp/themes/revealjs/templates/revealjs/static/js/reveal.js
sphinxjp/themes/revealjs/templates/revealjs/static/js/reveal.min.js
sphinxjp/themes/revealjs/templates/revealjs/static/lib/css/zenburn.css
sphinxjp/themes/revealjs/templates/revealjs/static/lib/font/league_gothic-webfont.eot
sphinxjp/themes/revealjs/templates/revealjs/static/lib/font/league_gothic-webfont.svg
sphinxjp.themes.revealjs-0.3.0.dist-info/DESCRIPTION.rst
sphinxjp.themes.revealjs-0.3.0.dist-info/entry_points.txt
sphinxjp.themes.revealjs-0.3.0.dist-info/METADATA
sphinxjp.themes.revealjs-0.3.0.dist-info/metadata.json
sphinxjp.themes.revealjs-0.3.0.dist-info/namespace_packages.txt
sphinxjp.themes.revealjs-0.3.0.dist-info/pbr.json
sphinxjp.themes.revealjs-0.3.0.dist-info/RECORD
sphinxjp.themes.revealjs-0.3.0.dist-info/top_level.txt
sphinxjp.themes.revealjs-0.3.0.dist-info/WHEEL
