Metadata-Version: 2.0
Name: sphinxjp.themes.revealjs
Version: 0.3.0
Summary: A sphinx theme for generate reveal.js presentation. #sphinxjp
Home-page: https://github.com/tell-k/sphinxjp.themes.revealjs
Author: tell-k
Author-email: ffk2005 at gmail dot com
License: MIT
Keywords: sphinx,reStructuredText,theme,presentation
Platform: UNKNOWN
Classifier: Development Status :: 4 - Beta
Classifier: License :: OSI Approved :: MIT License
Classifier: Programming Language :: Python
Classifier: Programming Language :: Python :: 2
Classifier: Programming Language :: Python :: 2.6
Classifier: Programming Language :: Python :: 2.7
Classifier: Programming Language :: Python :: 3
Classifier: Programming Language :: Python :: 3.3
Classifier: Programming Language :: Python :: 3.4
Classifier: Framework :: Sphinx
Classifier: Framework :: Sphinx :: Extension
Classifier: Framework :: Sphinx :: Theme
Classifier: Topic :: Software Development
Classifier: Topic :: Software Development :: Documentation
Classifier: Topic :: Text Processing :: Markup
Requires-Dist: setuptools
Requires-Dist: Sphinx
